py2sql_orm/__init__.py
py2sql_orm/orm.py
py2sql_orm/mapper/__init__.py
py2sql_orm/mapper/sql_mapping.py
py2sql_orm/mapper/utils.py
py2sql_orm/sql/__init__.py
py2sql_orm/sql/sql_column.py
py2sql_orm/sql/sql_types.py
py2sql_orm-0.1.2.dist-info/METADATA
py2sql_orm-0.1.2.dist-info/WHEEL
py2sql_orm-0.1.2.dist-info/top_level.txt
py2sql_orm-0.1.2.dist-info/RECORD
