Metadata-Version: 2.1
Name: py2sql-orm
Version: 0.1.2
Summary: Tool for fixing renamings, documentation in accordance with java code convention
Home-page: https://github.com/Pilipets/Metaprogramming/tree/main/TasksSolution/Py2SqlOrm
Author: Hlib Pylypets
License: MIT
Keywords: SQL,Python,ORM
Platform: UNKNOWN
Requires-Dist: cx-Oracle
